interop/CoreTests.py
interop/__init__.py
interop/__main__.py
interop/_py_interop_comm.pyd
interop/_py_interop_metrics.pyd
interop/_py_interop_plot.pyd
interop/_py_interop_run.pyd
interop/_py_interop_run_metrics.pyd
interop/_py_interop_summary.pyd
interop/_py_interop_table.pyd
interop/core.py
interop/py_interop_comm.py
interop/py_interop_metrics.py
interop/py_interop_plot.py
interop/py_interop_run.py
interop/py_interop_run_metrics.py
interop/py_interop_summary.py
interop/py_interop_table.py
interop-1.9.0.dist-info/METADATA
interop-1.9.0.dist-info/WHEEL
interop-1.9.0.dist-info/top_level.txt
interop-1.9.0.dist-info/RECORD
