Metadata-Version: 2.1
Name: interop
Version: 1.9.0
Summary: The Illumina InterOp libraries are a set of common routines used for reading InterOp metric files.
Home-page: https://github.com/Illumina/interop
Download-URL: https://github.com/Illumina/interop/releases/latest
Maintainer: Illumina Inc.
License: GPL
Keywords: Illumina sequencer HiSeqX HiSeq NextSeq MiniSeq NovaSeq MiSeq SBS genome
Classifier: Development Status :: 5 - Production/Stable
Classifier: Programming Language :: Python
Classifier: Programming Language :: Python :: 2
Classifier: Programming Language :: Python :: 3
Classifier: Topic :: Scientific/Engineering :: Bio-Informatics
Requires-Dist: numpy<2.0,>=1.16.6; python_version <= "3.8"
Requires-Dist: numpy>=1.21.6; python_version >= "3.10"
Requires-Dist: numpy>=1.23.2; python_version >= "3.11"
Requires-Dist: numpy>=1.26.2; python_version >= "3.12"
Requires-Dist: numpy>=1.19.3; python_version >= "3.9"
